[
  {
    "id": 1,
    "title": "Basic Greetings",
    "titleChinese": "基本问候",
    "level": "beginner",
    "completed": false,
    "locked": false,
    "description": "Learn essential greetings and polite expressions",
    "topics": ["你好", "再见", "谢谢", "对不起"],
    "content": {
      "introduction": "Welcome to your first Chinese lesson! Today we'll learn the most important greetings and polite expressions that you'll use every day.",
      "vocabulary": [
        {
          "character": "你好",
          "pinyin": "nǐ hǎo",
          "english": "hello",
          "example": "你好，很高兴见到你！"
        },
        {
          "character": "再见",
          "pinyin": "zài jiàn",
          "english": "goodbye",
          "example": "再见，明天见！"
        },
        {
          "character": "谢谢",
          "pinyin": "xiè xiè",
          "english": "thank you",
          "example": "谢谢你的帮助！"
        },
        {
          "character": "最近好吗",
          "pinyin": "zuìjìn hǎo ma",
          "english": "how have you been",
          "example": "小明，最近好吗？"
        },
        {
          "character": "对不起",
          "pinyin": "duì bù qǐ",
          "english": "sorry",
          "example": "对不起，我迟到了。"
        }
      ],
      "exercises": [
        {
          "type": "translation",
          "question": "How do you say 'hello' in Chinese?",
          "options": ["再见", "你好", "谢谢", "对不起"],
          "correct": 1
        },
        {
          "type": "pinyin",
          "question": "What is the pinyin for 谢谢?",
          "options": ["xiè xiè", "zài jiàn", "nǐ hǎo", "duì bù qǐ"],
          "correct": 0
        }
      ]
    }
  },
  {
    "id": 2,
    "title": "Numbers 1-10",
    "titleChinese": "数字一到十",
    "locked": false,
    "description": "Master counting from 1 to 10 in Mandarin",
    "topics": ["一", "二", "三", "四", "五"],
    "content": {
      "introduction": "Numbers are fundamental in any language. Let's learn to count from 1 to 10 in Chinese!",
      "vocabulary": [
        {
          "character": "一",
          "pinyin": "yī",
          "english": "one",
          "example": "我有一个苹果。"
        },
        {
          "character": "二",
          "pinyin": "èr",
          "english": "two",
          "example": "二加二等于四。"
        },
        {
          "character": "三",
          "pinyin": "sān",
          "english": "three",
          "example": "我们三个人一起去。"
        },
        {
          "character": "四",
          "pinyin": "sì",
          "english": "four",
          "example": "四季如春。"
        },
        {
          "character": "五",
          "pinyin": "wǔ",
          "english": "five",
          "example": "五点钟见面。"
        }
      ],
      "exercises": [
        {
          "type": "character",
          "question": "Which character represents the number 'three'?",
          "options": ["一", "二", "三", "四"],
          "correct": 2
        },
        {
          "type": "translation",
          "question": "What does 五 mean?",
          "options": ["four", "five", "six", "seven"],
          "correct": 1
        }
      ]
    }
  },
  {
    "id": 3,
    "title": "Family Members",
    "titleChinese": "家庭成员",
    "level": "beginner",
    "completed": false,
    "locked": false,
    "description": "Learn to talk about your family",
    "topics": ["爸爸", "妈妈", "兄弟", "姐妹"],
    "content": {
      "introduction": "Family is very important in Chinese culture. Let's learn how to talk about family members.",
      "vocabulary": [
        {
          "character": "爸爸",
          "pinyin": "bà ba",
          "english": "father, dad",
          "example": "我爸爸是医生。"
        },
        {
          "character": "妈妈",
          "english": "mother, mom",
          "audio": "/audio/mama.mp3",
          "example": "妈妈做饭很好吃。"
        },
        {
          "character": "哥哥",
          "english": "older brother",
          "audio": "/audio/gege.mp3",
          "example": "我哥哥比我高。"
        },
        {
          "character": "姐姐",
          "pinyin": "jiě jie",
          "english": "older sister",
          "example": "姐姐在大学学习。"
        }
      ],
      "exercises": [
        {
          "type": "translation",
          "question": "How do you say 'mother' in Chinese?",
          "options": ["爸爸", "妈妈", "哥哥", "姐姐"],
          "correct": 1
        },
        {
          "type": "pinyin",
          "question": "What is the pinyin for 哥哥?",
          "options": ["bà ba", "mā ma", "gē ge", "jiě jie"],
          "correct": 2
        }
      ]
    }
  },
  {
    "id": 4,
    "title": "Daily Activities",
    "titleChinese": "日常活动",
    "level": "intermediate",
    "completed": false,
    "locked": false,
    "description": "Express daily routines and activities",
    "topics": ["吃饭", "睡觉", "工作", "学习"],
    "content": {
      "introduction": "Learn to describe your daily activities and routines in Chinese.",
      "vocabulary": [
        {
          "character": "吃饭",
          "pinyin": "chī fàn",
          "english": "to eat (a meal)",
          "example": "我们一起吃饭吧。"
        },
        {
          "character": "睡觉",
          "pinyin": "shuì jiào",
          "english": "to sleep",
          "example": "我每天十点睡觉。"
        },
        {
          "character": "工作",
          "pinyin": "gōng zuò",
          "english": "to work",
          "example": "他在银行工作。"
        },
        {
          "character": "学习",
          "pinyin": "xué xí",
          "english": "to study",
          "example": "我正在学习中文。"
        }
      ],
      "exercises": [
        {
          "type": "translation",
          "question": "What does 工作 mean?",
          "options": ["to eat", "to sleep", "to work", "to study"],
          "correct": 2
        }
      ]
    }
  }
]
